anyio_serial/__init__.py
anyio_serial/_impl.py
anyio_serial-0.3.2.dist-info/METADATA
anyio_serial-0.3.2.dist-info/WHEEL
anyio_serial-0.3.2.dist-info/top_level.txt
anyio_serial-0.3.2.dist-info/zip-safe
anyio_serial-0.3.2.dist-info/RECORD
