Metadata-Version: 2.1
Name: anyio_serial
Version: 0.3.2
Summary: Quick and dirty serial bytestreams for anyio
Author: Matthias Urlichs
Author-email: matthias@urlichs.de
License: MIT
Project-URL: Source code, https://github.com/M-o-a-T/anyio_serial.git
Project-URL: Issue tracker, https://github.com/M-o-a-T/anyio_serial/issues
Classifier: Development Status :: 3 - Alpha
Classifier: Intended Audience :: Developers
Classifier: License :: OSI Approved :: MIT License
Classifier: Programming Language :: Python
Classifier: Programming Language :: Python :: 3
Classifier: Programming Language :: Python :: 3.6
Classifier: Programming Language :: Python :: 3.7
Classifier: Programming Language :: Python :: 3.8
Classifier: Programming Language :: Python :: 3.9
Requires-Python: >=3.6.2
Requires-Dist: anyio>=4.1
Requires-Dist: pyserial
